.coveragerc
.gitignore
.isort.cfg
.pre-commit-config.yaml
AUTHORS.rst
CHANGELOG.rst
LICENSE.txt
README.md
requirements.txt
setup.cfg
setup.py
docs/Makefile
docs/authors.rst
docs/changelog.rst
docs/conf.py
docs/index.rst
docs/license.rst
docs/_static/.gitignore
src/dortmund2array/__init__.py
src/dortmund2array/cli.py
src/dortmund2array/transform.py
src/dortmund2array.egg-info/PKG-INFO
src/dortmund2array.egg-info/SOURCES.txt
src/dortmund2array.egg-info/dependency_links.txt
src/dortmund2array.egg-info/entry_points.txt
src/dortmund2array.egg-info/not-zip-safe
src/dortmund2array.egg-info/requires.txt
src/dortmund2array.egg-info/top_level.txt
tests/conftest.py
tests/test_skeleton.py