Metadata-Version: 2.1
Name: dortmund2array
Version: 0.2
Summary: Add a short description here!
Home-page: https://github.com/LeviBorodenko/dortmund2array
Author: Levi Borodenko
Author-email: Levi.borodenko@gmail.com
License: mit
Project-URL: Documentation, https://github.com/LeviBorodenko/dortmund2array
Platform: any
Classifier: Development Status :: 4 - Beta
Classifier: Programming Language :: Python
Provides-Extra: testing
